usbsdmux/__init__.py
usbsdmux/__main__.py
usbsdmux/ctypehelper.py
usbsdmux/i2c_gpio.py
usbsdmux/mqtthelper.py
usbsdmux/sd_regs.py
usbsdmux/usb2642.py
usbsdmux/usb2642eeprom.py
usbsdmux/usbsdmux.py
usbsdmux-25.8.dist-info/licenses/AUTHORS
usbsdmux-25.8.dist-info/METADATA
usbsdmux-25.8.dist-info/WHEEL
usbsdmux-25.8.dist-info/entry_points.txt
usbsdmux-25.8.dist-info/top_level.txt
usbsdmux-25.8.dist-info/RECORD
