Metadata-Version: 2.4
Name: usbsdmux
Version: 25.8
Summary: Tool to control an USB-SD-Mux from the command line
Author-email: Chris Fiege <python@pengutronix.de>
License: LGPL-2.1-or-later
Project-URL: homepage, https://github.com/linux-automation/usbsdmux
Project-URL: documentation, https://www.linux-automation.com/usbsdmux-M01/
Classifier: Environment :: Console
Classifier: Natural Language :: English
Classifier: Operating System :: Unix
Classifier: Programming Language :: Python :: 3 :: Only
License-File: AUTHORS
Provides-Extra: mqtt
Requires-Dist: paho-mqtt; extra == "mqtt"
Dynamic: license-file
